metallurgy/__init__.py
metallurgy/_version.py
metallurgy/alloy.py
metallurgy/analyse.py
metallurgy/calculate.py
metallurgy/constants.py
metallurgy/density.py
metallurgy/enthalpy.py
metallurgy/entropy.py
metallurgy/generate.py
metallurgy/plots.py
metallurgy/price.py
metallurgy/properties.py
metallurgy/prototype.py
metallurgy/prototypes.py
metallurgy/py.typed
metallurgy/radii.py
metallurgy/ratios.py
metallurgy/rdf.py
metallurgy/valence.py
metallurgy/viscosity.py
metallurgy-0.0.33.dist-info/LICENSE
metallurgy-0.0.33.dist-info/METADATA
metallurgy-0.0.33.dist-info/WHEEL
metallurgy-0.0.33.dist-info/top_level.txt
metallurgy-0.0.33.dist-info/RECORD
